significance_analysis/__init__.py
significance_analysis/tools.py
significance_analysis-0.2.4.dist-info/LICENSE
significance_analysis-0.2.4.dist-info/METADATA
significance_analysis-0.2.4.dist-info/WHEEL
significance_analysis-0.2.4.dist-info/RECORD
