Metadata-Version: 2.1
Name: significance_analysis
Version: 0.2.4
Summary: Significance Analysis for HPO-algorithms performing on multiple benchmarks
License: MIT
Keywords: Hyperparameter Optimization,AutoML
Author: Anton Merlin Geburek
Author-email: gebureka@cs.uni-freiburg.de
Requires-Python: >=3.9,<3.13
Classifier: Intended Audience :: Science/Research
Classifier: License :: OSI Approved :: MIT License
Classifier: Natural Language :: English
Classifier: Operating System :: Microsoft :: Windows
Classifier: Programming Language :: Python :: 3
Classifier: Programming Language :: Python :: 3.9
Classifier: Programming Language :: Python :: 3.10
Classifier: Programming Language :: Python :: 3.11
Classifier: Programming Language :: Python :: 3.12
Classifier: Topic :: Scientific/Engineering :: Artificial Intelligence
Requires-Dist: matplotlib (<3.7.0)
Requires-Dist: pymer4 (>=0.8.0,<0.9.0)
Requires-Dist: typing-extensions (>=4.12.2,<5.0.0)
